{
  "algorithm": {
    "parameters": [
      {
        "name": "id",
        "type": "string"
      }
    ],
    "statements": [
      {
        "command": "Return",
        "expression": "RdsDelete(MyDataBase.TblUsers, id == ^id)"
      }
    ],
    "typeReturn": "any",
    "variables": []
  },
  "routing": {
    "method": "DELETE",
    "parameters": [
      {
        "bind": "id",
        "in": "Path",
        "name": "id",
        "remarks": "Id."
      }
    ],
    "path": "/user/{id}",
    "remarks": "Allows to delete a User.",
    "responses": []
  }
}